relast/__init__.py
relast/dom.py
relast/expr.py
relast/mesh.py
relast/relast.cp310-win_amd64.pyd
relast-0.1.5.data/data/README/README.md
relast-0.1.5.data/data/licenses/APACHE2
relast-0.1.5.data/data/licenses/MIT
relast-0.1.5.dist-info/LICENSE
relast-0.1.5.dist-info/METADATA
relast-0.1.5.dist-info/WHEEL
relast-0.1.5.dist-info/top_level.txt
relast-0.1.5.dist-info/RECORD
